phyber_numint/__init__.py
phyber_numint/integrators.py
phyber_numint/examples/__init__.py
phyber_numint/examples/examples.py
phyber_numint-0.1.2.dist-info/LICENSE
phyber_numint-0.1.2.dist-info/METADATA
phyber_numint-0.1.2.dist-info/WHEEL
phyber_numint-0.1.2.dist-info/top_level.txt
phyber_numint-0.1.2.dist-info/RECORD
