Metadata-Version: 2.1
Name: phyber-numint
Version: 0.1.2
Summary: A simple package to perform numerical integration easily
Home-page: https://github.com/lautisilber/Phyber_NumInt
Author: Lautaro Silbergleit
Author-email: lautisilbergleit@gmail.com
License: MIT
Platform: UNKNOWN
Classifier: License :: OSI Approved :: MIT License
Classifier: Programming Language :: Python :: 3
Classifier: Operating System :: OS Independent
Classifier: Intended Audience :: Education
Classifier: Intended Audience :: Science/Research
Classifier: Topic :: Scientific/Engineering
Classifier: Topic :: Scientific/Engineering :: Physics
Classifier: Topic :: Scientific/Engineering :: Visualization
Requires-Python: >=3.7
Requires-Dist: numpy >=1.20
